[
  {
    "DATE_CT": "2025-11-07T00:00:00",
    "MATURITE": 0.0027397260273972603,
    "TAUX_ZC_EXPO": 0.0739389064903,
    "TAUX_ZC_ACTUARIEL_365": 0.0767410215987,
    "ZERO_COUPON": 0.9997974481698,
    "TAUX_IN_FINE": 0.0,
    "TAUX_FORWARD_INSTANTANE": 0.0767782691192,
    "ID_CURVE": 6050
  },
  {
    "DATE_CT": "2025-11-07T00:00:00",
    "MATURITE": 1.0,
    "TAUX_ZC_EXPO": 0.0828494449363,
    "TAUX_ZC_ACTUARIEL_365": 0.0863782364907,
    "ZERO_COUPON": 0.9204897211769,
    "TAUX_IN_FINE": 0.0863782364907,
    "TAUX_FORWARD_INSTANTANE": 0.0929537791347,
    "ID_CURVE": 6050
  },
  {
    "DATE_CT": "2025-11-07T00:00:00",
    "MATURITE": 2.0,
    "TAUX_ZC_EXPO": 0.0870961123352,
    "TAUX_ZC_ACTUARIEL_365": 0.0910015333844,
    "ZERO_COUPON": 0.8401353873878,
    "TAUX_IN_FINE": 0.0907999163675,
    "TAUX_FORWARD_INSTANTANE": 0.097226060086,
    "ID_CURVE": 6050
  },
  {
    "DATE_CT": "2025-11-07T00:00:00",
    "MATURITE": 3.0,
    "TAUX_ZC_EXPO": 0.0890822807329,
    "TAUX_ZC_ACTUARIEL_365": 0.0931705995041,
    "ZERO_COUPON": 0.7654840943656,
    "TAUX_IN_FINE": 0.092836804269,
    "TAUX_FORWARD_INSTANTANE": 0.0974893919995,
    "ID_CURVE": 6050
  },
  {
    "DATE_CT": "2025-11-07T00:00:00",
    "MATURITE": 4.0,
    "TAUX_ZC_EXPO": 0.0899873230013,
    "TAUX_ZC_ACTUARIEL_365": 0.0941604129471,
    "ZERO_COUPON": 0.6977117047356,
    "TAUX_IN_FINE": 0.0937670869202,
    "TAUX_FORWARD_INSTANTANE": 0.0967268375024,
    "ID_CURVE": 6050
  },
  {
    "DATE_CT": "2025-11-07T00:00:00",
    "MATURITE": 5.0,
    "TAUX_ZC_EXPO": 0.0903800446525,
    "TAUX_ZC_ACTUARIEL_365": 0.0945901978186,
    "ZERO_COUPON": 0.6364176662358,
    "TAUX_IN_FINE": 0.0941864930894,
    "TAUX_FORWARD_INSTANTANE": 0.0959203605194,
    "ID_CURVE": 6050
  },
  {
    "DATE_CT": "2025-11-07T00:00:00",
    "MATURITE": 6.0,
    "TAUX_ZC_EXPO": 0.0905335785375,
    "TAUX_ZC_ACTUARIEL_365": 0.0947582674061,
    "ZERO_COUPON": 0.5808855838432,
    "TAUX_IN_FINE": 0.094371245043,
    "TAUX_FORWARD_INSTANTANE": 0.0953150460423,
    "ID_CURVE": 6050
  },
  {
    "DATE_CT": "2025-11-07T00:00:00",
    "MATURITE": 7.0,
    "TAUX_ZC_EXPO": 0.0905782235462,
    "TAUX_ZC_ACTUARIEL_365": 0.0948071439894,
    "ZERO_COUPON": 0.5304404579553,
    "TAUX_IN_FINE": 0.0944490474009,
    "TAUX_FORWARD_INSTANTANE": 0.0949163510646,
    "ID_CURVE": 6050
  },
  {
    "DATE_CT": "2025-11-07T00:00:00",
    "MATURITE": 8.0,
    "TAUX_ZC_EXPO": 0.0905755162228,
    "TAUX_ZC_ACTUARIEL_365": 0.0948041799965,
    "ZERO_COUPON": 0.4845163365827,
    "TAUX_IN_FINE": 0.0944787417792,
    "TAUX_FORWARD_INSTANTANE": 0.0946713706449,
    "ID_CURVE": 6050
  },
  {
    "DATE_CT": "2025-11-07T00:00:00",
    "MATURITE": 9.0,
    "TAUX_ZC_EXPO": 0.0905540554651,
    "TAUX_ZC_ACTUARIEL_365": 0.0947806849213,
    "ZERO_COUPON": 0.4426453033929,
    "TAUX_IN_FINE": 0.0944872964855,
    "TAUX_FORWARD_INSTANTANE": 0.0945272083902,
    "ID_CURVE": 6050
  },
  {
    "DATE_CT": "2025-11-07T00:00:00",
    "MATURITE": 10.0,
    "TAUX_ZC_EXPO": 0.0905267799386,
    "TAUX_ZC_ACTUARIEL_365": 0.0947508246089,
    "ZERO_COUPON": 0.4044335635396,
    "TAUX_IN_FINE": 0.0944869642437,
    "TAUX_FORWARD_INSTANTANE": 0.0944448419208,
    "ID_CURVE": 6050
  },
  {
    "DATE_CT": "2025-11-07T00:00:00",
    "MATURITE": 11.0,
    "TAUX_ZC_EXPO": 0.0904992670718,
    "TAUX_ZC_ACTUARIEL_365": 0.0947207052897,
    "ZERO_COUPON": 0.3695416083394,
    "TAUX_IN_FINE": 0.0944832311929,
    "TAUX_FORWARD_INSTANTANE": 0.0943987813664,
    "ID_CURVE": 6050
  },
  {
    "DATE_CT": "2025-11-07T00:00:00",
    "MATURITE": 12.0,
    "TAUX_ZC_EXPO": 0.0904736961992,
    "TAUX_ZC_ACTUARIEL_365": 0.0946927126839,
    "ZERO_COUPON": 0.3376706204326,
    "TAUX_IN_FINE": 0.0944784920163,
    "TAUX_FORWARD_INSTANTANE": 0.0943734403355,
    "ID_CURVE": 6050
  },
  {
    "DATE_CT": "2025-11-07T00:00:00",
    "MATURITE": 13.0,
    "TAUX_ZC_EXPO": 0.0904507248308,
    "TAUX_ZC_ACTUARIEL_365": 0.0946675663831,
    "ZERO_COUPON": 0.3085536876311,
    "TAUX_IN_FINE": 0.0944737434626,
    "TAUX_FORWARD_INSTANTANE": 0.0943596760871,
    "ID_CURVE": 6050
  },
  {
    "DATE_CT": "2025-11-07T00:00:00",
    "MATURITE": 14.0,
    "TAUX_ZC_EXPO": 0.0904303652511,
    "TAUX_ZC_ACTUARIEL_365": 0.0946452796384,
    "ZERO_COUPON": 0.2819501170694,
    "TAUX_IN_FINE": 0.0944693607483,
    "TAUX_FORWARD_INSTANTANE": 0.0943522767953,
    "ID_CURVE": 6050
  },
  {
    "DATE_CT": "2025-11-07T00:00:00",
    "MATURITE": 15.0,
    "TAUX_ZC_EXPO": 0.0904123855241,
    "TAUX_ZC_ACTUARIEL_365": 0.0946255983921,
    "ZERO_COUPON": 0.2576416062466,
    "TAUX_IN_FINE": 0.0944654507205,
    "TAUX_FORWARD_INSTANTANE": 0.0943483328687,
    "ID_CURVE": 6050
  },
  {
    "DATE_CT": "2025-11-07T00:00:00",
    "MATURITE": 16.0,
    "TAUX_ZC_EXPO": 0.0903964865338,
    "TAUX_ZC_ACTUARIEL_365": 0.0946081950887,
    "ZERO_COUPON": 0.2354294973773,
    "TAUX_IN_FINE": 0.0944620105308,
    "TAUX_FORWARD_INSTANTANE": 0.0943462456509,
    "ID_CURVE": 6050
  },
  {
    "DATE_CT": "2025-11-07T00:00:00",
    "MATURITE": 17.0,
    "TAUX_ZC_EXPO": 0.0903823751977,
    "TAUX_ZC_ACTUARIEL_365": 0.0945927488135,
    "ZERO_COUPON": 0.2151326685016,
    "TAUX_IN_FINE": 0.0944589974989,
    "TAUX_FORWARD_INSTANTANE": 0.0943451477289,
    "ID_CURVE": 6050
  },
  {
    "DATE_CT": "2025-11-07T00:00:00",
    "MATURITE": 18.0,
    "TAUX_ZC_EXPO": 0.0903697907437,
    "TAUX_ZC_ACTUARIEL_365": 0.0945789740481,
    "ZERO_COUPON": 0.1965858134394,
    "TAUX_IN_FINE": 0.0944563588108,
    "TAUX_FORWARD_INSTANTANE": 0.0943445732057,
    "ID_CURVE": 6050
  },
  {
    "DATE_CT": "2025-11-07T00:00:00",
    "MATURITE": 19.0,
    "TAUX_ZC_EXPO": 0.0903585106641,
    "TAUX_ZC_ACTUARIEL_365": 0.0945666271797,
    "ZERO_COUPON": 0.1796379751354,
    "TAUX_IN_FINE": 0.094454043321,
    "TAUX_FORWARD_INSTANTANE": 0.0943442739301,
    "ID_CURVE": 6050
  },
  {
    "DATE_CT": "2025-11-07T00:00:00",
    "MATURITE": 20.0,
    "TAUX_ZC_EXPO": 0.0903483485624,
    "TAUX_ZC_ACTUARIEL_365": 0.0945555041389,
    "ZERO_COUPON": 0.1641512580155,
    "TAUX_IN_FINE": 0.0944520055779,
    "TAUX_FORWARD_INSTANTANE": 0.0943441186541,
    "ID_CURVE": 6050
  }
]