[
  {
    "DATE_CT": "2025-11-18T00:00:00",
    "MATURITE": 0.0027397260273972603,
    "TAUX_ZC_EXPO": 0.0735472230972,
    "TAUX_ZC_ACTUARIEL_365": 0.0763193626056,
    "ZERO_COUPON": 0.9997985210582,
    "TAUX_IN_FINE": 0.0,
    "TAUX_FORWARD_INSTANTANE": 0.0763569641153,
    "ID_CURVE": 6057
  },
  {
    "DATE_CT": "2025-11-18T00:00:00",
    "MATURITE": 1.0,
    "TAUX_ZC_EXPO": 0.0825667716774,
    "TAUX_ZC_ACTUARIEL_365": 0.0860711898131,
    "ZERO_COUPON": 0.9207499557852,
    "TAUX_IN_FINE": 0.0860711898131,
    "TAUX_FORWARD_INSTANTANE": 0.0927481660039,
    "ID_CURVE": 6057
  },
  {
    "DATE_CT": "2025-11-18T00:00:00",
    "MATURITE": 2.0,
    "TAUX_ZC_EXPO": 0.0868952393666,
    "TAUX_ZC_ACTUARIEL_365": 0.0907824026771,
    "ZERO_COUPON": 0.8404729761744,
    "TAUX_IN_FINE": 0.0905774169361,
    "TAUX_FORWARD_INSTANTANE": 0.0971596097068,
    "ID_CURVE": 6057
  },
  {
    "DATE_CT": "2025-11-18T00:00:00",
    "MATURITE": 3.0,
    "TAUX_ZC_EXPO": 0.0889419686104,
    "TAUX_ZC_ACTUARIEL_365": 0.0930172251775,
    "ZERO_COUPON": 0.7658063822862,
    "TAUX_IN_FINE": 0.0926754653749,
    "TAUX_FORWARD_INSTANTANE": 0.0975062977141,
    "ID_CURVE": 6057
  },
  {
    "DATE_CT": "2025-11-18T00:00:00",
    "MATURITE": 4.0,
    "TAUX_ZC_EXPO": 0.0898919230324,
    "TAUX_ZC_ACTUARIEL_365": 0.0940560350567,
    "ZERO_COUPON": 0.6979780022415,
    "TAUX_IN_FINE": 0.0936500194014,
    "TAUX_FORWARD_INSTANTANE": 0.0967917302749,
    "ID_CURVE": 6057
  },
  {
    "DATE_CT": "2025-11-18T00:00:00",
    "MATURITE": 5.0,
    "TAUX_ZC_EXPO": 0.0903182593884,
    "TAUX_ZC_ACTUARIEL_365": 0.0945225703633,
    "ZERO_COUPON": 0.6366143027752,
    "TAUX_IN_FINE": 0.0941018393444,
    "TAUX_FORWARD_INSTANTANE": 0.0960121923845,
    "ID_CURVE": 6057
  },
  {
    "DATE_CT": "2025-11-18T00:00:00",
    "MATURITE": 6.0,
    "TAUX_ZC_EXPO": 0.090497303026,
    "TAUX_ZC_ACTUARIEL_365": 0.0947185552102,
    "ZERO_COUPON": 0.5810120291336,
    "TAUX_IN_FINE": 0.0943107183771,
    "TAUX_FORWARD_INSTANTANE": 0.0954217361658,
    "ID_CURVE": 6057
  },
  {
    "DATE_CT": "2025-11-18T00:00:00",
    "MATURITE": 7.0,
    "TAUX_ZC_EXPO": 0.0905616285085,
    "TAUX_ZC_ACTUARIEL_365": 0.0947889757744,
    "ZERO_COUPON": 0.53050208029,
    "TAUX_IN_FINE": 0.0944068180166,
    "TAUX_FORWARD_INSTANTANE": 0.0950311275283,
    "ID_CURVE": 6057
  },
  {
    "DATE_CT": "2025-11-18T00:00:00",
    "MATURITE": 8.0,
    "TAUX_ZC_EXPO": 0.0905743740572,
    "TAUX_ZC_ACTUARIEL_365": 0.0948029295495,
    "ZERO_COUPON": 0.4845207637863,
    "TAUX_IN_FINE": 0.0944506560508,
    "TAUX_FORWARD_INSTANTANE": 0.0947905015146,
    "ID_CURVE": 6057
  },
  {
    "DATE_CT": "2025-11-18T00:00:00",
    "MATURITE": 9.0,
    "TAUX_ZC_EXPO": 0.0905652627221,
    "TAUX_ZC_ACTUARIEL_365": 0.0947929544785,
    "ZERO_COUPON": 0.4426006580877,
    "TAUX_IN_FINE": 0.0944703472559,
    "TAUX_FORWARD_INSTANTANE": 0.0946486637432,
    "ID_CURVE": 6057
  },
  {
    "DATE_CT": "2025-11-18T00:00:00",
    "MATURITE": 10.0,
    "TAUX_ZC_EXPO": 0.0905480251325,
    "TAUX_ZC_ACTUARIEL_365": 0.0947740830495,
    "ZERO_COUPON": 0.4043476499714,
    "TAUX_IN_FINE": 0.0944789354566,
    "TAUX_FORWARD_INSTANTANE": 0.0945675291171,
    "ID_CURVE": 6057
  },
  {
    "DATE_CT": "2025-11-18T00:00:00",
    "MATURITE": 11.0,
    "TAUX_ZC_EXPO": 0.0905288012671,
    "TAUX_ZC_ACTUARIEL_365": 0.0947530374622,
    "ZERO_COUPON": 0.3694215725848,
    "TAUX_IN_FINE": 0.0944824596371,
    "TAUX_FORWARD_INSTANTANE": 0.0945221173268,
    "ID_CURVE": 6057
  },
  {
    "DATE_CT": "2025-11-18T00:00:00",
    "MATURITE": 12.0,
    "TAUX_ZC_EXPO": 0.0905101745847,
    "TAUX_ZC_ACTUARIEL_365": 0.094732646035,
    "ZERO_COUPON": 0.3375228406308,
    "TAUX_IN_FINE": 0.0944837066921,
    "TAUX_FORWARD_INSTANTANE": 0.0944971161504,
    "ID_CURVE": 6057
  },
  {
    "DATE_CT": "2025-11-18T00:00:00",
    "MATURITE": 13.0,
    "TAUX_ZC_EXPO": 0.0904930967805,
    "TAUX_ZC_ACTUARIEL_365": 0.0947139505649,
    "ZERO_COUPON": 0.3083837721557,
    "TAUX_IN_FINE": 0.0944839562297,
    "TAUX_FORWARD_INSTANTANE": 0.094483529107,
    "ID_CURVE": 6057
  },
  {
    "DATE_CT": "2025-11-18T00:00:00",
    "MATURITE": 14.0,
    "TAUX_ZC_EXPO": 0.0904777973895,
    "TAUX_ZC_ACTUARIEL_365": 0.0946972022362,
    "ZERO_COUPON": 0.2817629502628,
    "TAUX_IN_FINE": 0.0944837909551,
    "TAUX_FORWARD_INSTANTANE": 0.0944762218355,
    "ID_CURVE": 6057
  },
  {
    "DATE_CT": "2025-11-18T00:00:00",
    "MATURITE": 15.0,
    "TAUX_ZC_EXPO": 0.0904642073036,
    "TAUX_ZC_ACTUARIEL_365": 0.0946823253083,
    "ZERO_COUPON": 0.2574414123672,
    "TAUX_IN_FINE": 0.0944834725113,
    "TAUX_FORWARD_INSTANTANE": 0.0944723255213,
    "ID_CURVE": 6057
  },
  {
    "DATE_CT": "2025-11-18T00:00:00",
    "MATURITE": 16.0,
    "TAUX_ZC_EXPO": 0.0904521512571,
    "TAUX_ZC_ACTUARIEL_365": 0.0946691278468,
    "ZERO_COUPON": 0.2352199088396,
    "TAUX_IN_FINE": 0.0944831154399,
    "TAUX_FORWARD_INSTANTANE": 0.0944702628595,
    "ID_CURVE": 6057
  },
  {
    "DATE_CT": "2025-11-18T00:00:00",
    "MATURITE": 17.0,
    "TAUX_ZC_EXPO": 0.0904414317273,
    "TAUX_ZC_ACTUARIEL_365": 0.0946573935714,
    "ZERO_COUPON": 0.2149167920757,
    "TAUX_IN_FINE": 0.0944827674779,
    "TAUX_FORWARD_INSTANTANE": 0.0944691775657,
    "ID_CURVE": 6057
  },
  {
    "DATE_CT": "2025-11-18T00:00:00",
    "MATURITE": 18.0,
    "TAUX_ZC_EXPO": 0.0904318626848,
    "TAUX_ZC_ACTUARIEL_365": 0.0946469187984,
    "ZERO_COUPON": 0.1963662917632,
    "TAUX_IN_FINE": 0.0944824464706,
    "TAUX_FORWARD_INSTANTANE": 0.0944686095199,
    "ID_CURVE": 6057
  },
  {
    "DATE_CT": "2025-11-18T00:00:00",
    "MATURITE": 19.0,
    "TAUX_ZC_EXPO": 0.0904232808341,
    "TAUX_ZC_ACTUARIEL_365": 0.0946375247423,
    "ZERO_COUPON": 0.179417042645,
    "TAUX_IN_FINE": 0.0944821572371,
    "TAUX_FORWARD_INSTANTANE": 0.0944683135589,
    "ID_CURVE": 6057
  },
  {
    "DATE_CT": "2025-11-18T00:00:00",
    "MATURITE": 20.0,
    "TAUX_ZC_EXPO": 0.09041554725,
    "TAUX_ZC_ACTUARIEL_365": 0.0946290593036,
    "ZERO_COUPON": 0.1639307912174,
    "TAUX_IN_FINE": 0.0944818992004,
    "TAUX_FORWARD_INSTANTANE": 0.0944681599755,
    "ID_CURVE": 6057
  }
]