[
  {
    "DATE_CT": "2025-09-08T00:00:00",
    "MATURITE": 0.0027397260273972603,
    "TAUX_ZC_EXPO": 0.0738128674898,
    "TAUX_ZC_ACTUARIEL_365": 0.0766053187887,
    "ZERO_COUPON": 0.9997977934123,
    "TAUX_IN_FINE": 0.0,
    "TAUX_FORWARD_INSTANTANE": 0.076649757675,
    "ID_CURVE": 5998
  },
  {
    "DATE_CT": "2025-09-08T00:00:00",
    "MATURITE": 1.0,
    "TAUX_ZC_EXPO": 0.0842318225234,
    "TAUX_ZC_ACTUARIEL_365": 0.0878810599112,
    "ZERO_COUPON": 0.9192181359253,
    "TAUX_IN_FINE": 0.0878810599112,
    "TAUX_FORWARD_INSTANTANE": 0.0953518370875,
    "ID_CURVE": 5998
  },
  {
    "DATE_CT": "2025-09-08T00:00:00",
    "MATURITE": 2.0,
    "TAUX_ZC_EXPO": 0.0888914586744,
    "TAUX_ZC_ACTUARIEL_365": 0.0929620183416,
    "ZERO_COUPON": 0.8371241288908,
    "TAUX_IN_FINE": 0.0927358376394,
    "TAUX_FORWARD_INSTANTANE": 0.0994597319893,
    "ID_CURVE": 5998
  },
  {
    "DATE_CT": "2025-09-08T00:00:00",
    "MATURITE": 3.0,
    "TAUX_ZC_EXPO": 0.0908421746151,
    "TAUX_ZC_ACTUARIEL_365": 0.0950961576464,
    "ZERO_COUPON": 0.7614532322395,
    "TAUX_IN_FINE": 0.0947442983513,
    "TAUX_FORWARD_INSTANTANE": 0.0989453398022,
    "ID_CURVE": 5998
  },
  {
    "DATE_CT": "2025-09-08T00:00:00",
    "MATURITE": 4.0,
    "TAUX_ZC_EXPO": 0.0915535750846,
    "TAUX_ZC_ACTUARIEL_365": 0.0958754867417,
    "ZERO_COUPON": 0.6933541992481,
    "TAUX_IN_FINE": 0.0954940845968,
    "TAUX_FORWARD_INSTANTANE": 0.0974644699975,
    "ID_CURVE": 5998
  },
  {
    "DATE_CT": "2025-09-08T00:00:00",
    "MATURITE": 5.0,
    "TAUX_ZC_EXPO": 0.0917174811238,
    "TAUX_ZC_ACTUARIEL_365": 0.0960551220735,
    "ZERO_COUPON": 0.632176023373,
    "TAUX_IN_FINE": 0.0957046067534,
    "TAUX_FORWARD_INSTANTANE": 0.0961430733672,
    "ID_CURVE": 5998
  },
  {
    "DATE_CT": "2025-09-08T00:00:00",
    "MATURITE": 6.0,
    "TAUX_ZC_EXPO": 0.0916547896408,
    "TAUX_ZC_ACTUARIEL_365": 0.0959864109063,
    "ZERO_COUPON": 0.5769909265322,
    "TAUX_IN_FINE": 0.0956965546417,
    "TAUX_FORWARD_INSTANTANE": 0.0952064954284,
    "ID_CURVE": 5998
  },
  {
    "DATE_CT": "2025-09-08T00:00:00",
    "MATURITE": 7.0,
    "TAUX_ZC_EXPO": 0.0915108707114,
    "TAUX_ZC_ACTUARIEL_365": 0.0958286890652,
    "ZERO_COUPON": 0.5269887410084,
    "TAUX_IN_FINE": 0.0956098768865,
    "TAUX_FORWARD_INSTANTANE": 0.0946071403,
    "ID_CURVE": 5998
  },
  {
    "DATE_CT": "2025-09-08T00:00:00",
    "MATURITE": 8.0,
    "TAUX_ZC_EXPO": 0.0913489775881,
    "TAUX_ZC_ACTUARIEL_365": 0.0956512962958,
    "ZERO_COUPON": 0.4815275556079,
    "TAUX_IN_FINE": 0.0955034811077,
    "TAUX_FORWARD_INSTANTANE": 0.0942451960571,
    "ID_CURVE": 5998
  },
  {
    "DATE_CT": "2025-09-08T00:00:00",
    "MATURITE": 9.0,
    "TAUX_ZC_EXPO": 0.091194614367,
    "TAUX_ZC_ACTUARIEL_365": 0.0954821810855,
    "ZERO_COUPON": 0.4401007815577,
    "TAUX_IN_FINE": 0.0954005011364,
    "TAUX_FORWARD_INSTANTANE": 0.0940346555873,
    "ID_CURVE": 5998
  },
  {
    "DATE_CT": "2025-09-08T00:00:00",
    "MATURITE": 10.0,
    "TAUX_ZC_EXPO": 0.0910564150307,
    "TAUX_ZC_ACTUARIEL_365": 0.095330796636,
    "ZERO_COUPON": 0.4022972039117,
    "TAUX_IN_FINE": 0.0953086886646,
    "TAUX_FORWARD_INSTANTANE": 0.0939153544081,
    "ID_CURVE": 5998
  },
  {
    "DATE_CT": "2025-09-08T00:00:00",
    "MATURITE": 11.0,
    "TAUX_ZC_EXPO": 0.0909358345611,
    "TAUX_ZC_ACTUARIEL_365": 0.0951987290967,
    "ZERO_COUPON": 0.367771234251,
    "TAUX_IN_FINE": 0.0952294863399,
    "TAUX_FORWARD_INSTANTANE": 0.093849051536,
    "ID_CURVE": 5998
  },
  {
    "DATE_CT": "2025-09-08T00:00:00",
    "MATURITE": 12.0,
    "TAUX_ZC_EXPO": 0.0908315523207,
    "TAUX_ZC_ACTUARIEL_365": 0.0950845252744,
    "ZERO_COUPON": 0.3362236794534,
    "TAUX_IN_FINE": 0.0951619826486,
    "TAUX_FORWARD_INSTANTANE": 0.0938127491394,
    "ID_CURVE": 5998
  },
  {
    "DATE_CT": "2025-09-08T00:00:00",
    "MATURITE": 13.0,
    "TAUX_ZC_EXPO": 0.0907414042519,
    "TAUX_ZC_ACTUARIEL_365": 0.0949858099688,
    "ZERO_COUPON": 0.3073899151715,
    "TAUX_IN_FINE": 0.0951045761472,
    "TAUX_FORWARD_INSTANTANE": 0.0937931069315,
    "ID_CURVE": 5998
  },
  {
    "DATE_CT": "2025-09-08T00:00:00",
    "MATURITE": 14.0,
    "TAUX_ZC_EXPO": 0.0906631794973,
    "TAUX_ZC_ACTUARIEL_365": 0.0949001583226,
    "ZERO_COUPON": 0.2810326250628,
    "TAUX_IN_FINE": 0.095055631701,
    "TAUX_FORWARD_INSTANTANE": 0.0937825810334,
    "ID_CURVE": 5998
  },
  {
    "DATE_CT": "2025-09-08T00:00:00",
    "MATURITE": 15.0,
    "TAUX_ZC_EXPO": 0.0905949088286,
    "TAUX_ZC_ACTUARIEL_365": 0.0948254113082,
    "ZERO_COUPON": 0.2569371870234,
    "TAUX_IN_FINE": 0.0950137053544,
    "TAUX_FORWARD_INSTANTANE": 0.0937769852974,
    "ID_CURVE": 5998
  },
  {
    "DATE_CT": "2025-09-08T00:00:00",
    "MATURITE": 16.0,
    "TAUX_ZC_EXPO": 0.0905349355528,
    "TAUX_ZC_ACTUARIEL_365": 0.0947597530108,
    "ZERO_COUPON": 0.2349085548549,
    "TAUX_IN_FINE": 0.094977593349,
    "TAUX_FORWARD_INSTANTANE": 0.093774030478,
    "ID_CURVE": 5998
  },
  {
    "DATE_CT": "2025-09-08T00:00:00",
    "MATURITE": 17.0,
    "TAUX_ZC_EXPO": 0.0904819007584,
    "TAUX_ZC_ACTUARIEL_365": 0.0947016941919,
    "ZERO_COUPON": 0.2147689858612,
    "TAUX_IN_FINE": 0.0949463159391,
    "TAUX_FORWARD_INSTANTANE": 0.093772479137,
    "ID_CURVE": 5998
  },
  {
    "DATE_CT": "2025-09-08T00:00:00",
    "MATURITE": 18.0,
    "TAUX_ZC_EXPO": 0.090434700738,
    "TAUX_ZC_ACTUARIEL_365": 0.094650025469,
    "ZERO_COUPON": 0.1963562606557,
    "TAUX_IN_FINE": 0.0949190821229,
    "TAUX_FORWARD_INSTANTANE": 0.0937716686874,
    "ID_CURVE": 5998
  },
  {
    "DATE_CT": "2025-09-08T00:00:00",
    "MATURITE": 19.0,
    "TAUX_ZC_EXPO": 0.0903924405013,
    "TAUX_ZC_ACTUARIEL_365": 0.0946037662773,
    "ZERO_COUPON": 0.1795222057977,
    "TAUX_IN_FINE": 0.0948952532121,
    "TAUX_FORWARD_INSTANTANE": 0.0937712471246,
    "ID_CURVE": 5998
  },
  {
    "DATE_CT": "2025-09-08T00:00:00",
    "MATURITE": 20.0,
    "TAUX_ZC_EXPO": 0.0903543921608,
    "TAUX_ZC_ACTUARIEL_365": 0.0945621192128,
    "ZERO_COUPON": 0.1641314179288,
    "TAUX_IN_FINE": 0.0948743112281,
    "TAUX_FORWARD_INSTANTANE": 0.09377102868,
    "ID_CURVE": 5998
  }
]